etc/bitflag_data.json
etc/cap_data.json
etc/type_data.json
squinnie/__init__.py
squinnie/cap_translator.py
squinnie/crowbar.py
squinnie/dio.py
squinnie/dumper.py
squinnie/errors.py
squinnie/file_mode.py
squinnie/helper.py
squinnie/ldump.py
squinnie/network_config.py
squinnie/nwiface_translator.py
squinnie/probe.py
squinnie/types.py
squinnie/viewer.py
squinnie/daw/__init__.py
squinnie/daw/accounts.py
squinnie/daw/factory.py
squinnie/daw/fs.py
squinnie/daw/helper.py
squinnie/daw/namespaces.py
squinnie/daw/networkInterfaces.py
squinnie/daw/networking.py
squinnie/daw/proc.py
squinnie/daw/sockets.py
squinnie/daw/systemdata.py
squinnie/daw/sysv.py
squinnie_security-0.5.1.data/scripts/squinnie
squinnie_security-0.5.1.dist-info/LICENSE
squinnie_security-0.5.1.dist-info/METADATA
squinnie_security-0.5.1.dist-info/WHEEL
squinnie_security-0.5.1.dist-info/top_level.txt
squinnie_security-0.5.1.dist-info/RECORD
