Metadata-Version: 2.1
Name: squinnie-security
Version: 0.5.1
Summary: Squinnie is a security oriented system scanning utility for Linux
Home-page: https://github.com/mgerstner/squinnie
Author: Matthias Gerstner
Author-email: matthias.gerstner@suse.com
License: GPL2
Keywords: openSUSE security scanner review audit
Platform: UNKNOWN
Classifier: Intended Audience :: Developers
Classifier: License :: OSI Approved :: GNU General Public License v2 (GPLv2)
Classifier: Programming Language :: Python :: 2.7
Classifier: Topic :: Security
Requires-Dist: execnet
Requires-Dist: terminaltables
Requires-Dist: termcolor
